{
  "Result": [
    {
      "ObjectMainGroupDescription": null,
      "ObjectSubGroupDescription": null,
      "RowId": "ab6c8aff-b523-44f0-a485-5b3418704348",
      "SyndicateNo": 1,
      "CompanyNo": 1,
      "AreaNo": "11",
      "HouseNo": "11-069",
      "EntranceNo": "11-069-01",
      "ObjectNo": "11-069-01-0048",
      "ObjectMainGroupNo": 1,
      "ObjectSubGroupNo": 3,
      "ObjectTypeDescription": "3 rum och kök",
      "ObjectAreaSort": 82,
      "ObjectSubDescription": "3 Rum",
      "ObjectArea": "82",
      "ObjectFloor": "4  ",
      "SeekAreaNo": 12,
      "MarketPlaceNo": 107,
      "HouseFormNo": null,
      "PropertyNo": 4,
      "RentPerMonthSort": 5653,
      "RentPerMonth": "5 653",
      "FirstEstateImageUrl": "/vatterhem/files/jpg/thumbs/thumbM5958.jpg",
      "BoardNo": "",
      "Description": "",
      "PlaceName": "Jönköping",
      "SeekAreaDescription": "Råslätt",
      "StreetName": "Kärrhöksgatan",
      "StreetNo": 4,
      "StreetChar": "",
      "MarketPlaceDescription": "Torget",
      "CountInterest": 109,
      "FirstInfoTextShort": "<p class=\"MsoNormal\" style=\"margin: 5pt 0cm;\"><span style=\"font-weight: bold;\">Välkommen till Råslätt<br></span>Väl inbäddad mellan Lockebos ängar och Lillåns dalgång hittar du Råslätt, Här trivs mångfalden, här bor Råslättsandan; välkomnande och äkta. Här finns variationer i lägenheter för både den lilla och stora familjen. Hit söker sig såväl studenter som vill bo på Jönköpings störst samlade...",
      "FirstInfoText": "<p class=\"MsoNormal\" style=\"margin: 5pt 0cm;\"><span style=\"font-weight: bold;\">Välkommen till Råslätt<br></span>Väl inbäddad mellan Lockebos ängar och Lillåns dalgång hittar du Råslätt, Här trivs mångfalden, här bor Råslättsandan; välkomnande och äkta. Här finns variationer i lägenheter för både den lilla och stora familjen. Hit söker sig såväl studenter som vill bo på Jönköpings störst samlade studentområde som pensionärer som söker tryggheten och det sociala livet runt boulbanan. Råslätt har något för alla. Alltid med en tilltalande närhet till modern service och ett levande centrum. </p><p class=\"MsoNormal\" style=\"margin: 5pt 0cm;\"><br></p>",
      "EndPeriodMP": "2021-01-31T23:59:59",
      "EndPeriodMPDateString": "2021-01-31",
      "QueueDate": "2016-11-07T00:00:00",
      "QueueDateString": "2016-11-07",
      "QueuePoints": 3082,
      "QueuePositionCut": 5,
      "FreeFrom": "2021-05-01",
      "DesiredFreeFrom": null,
      "DesiredFreeFromString": "",
      "SeekAreaUrl": "https://vatterhem.se/jag-soker-ledigt/vara-omraden/jonkoping/raslatt/",
      "Latitude": "57,7373188",
      "Longitude": "14,1502756",
      "ArriveMarketPlace": "2021-01-25T15:47:00.397",
      "ArriveMarketPlaceDateString": "2021-01-25",
      "PublishingDate": "2021-01-25T15:45:13.13",
      "PublishingDateString": "2021-01-25",
      "IsTradingAdvertisement": false,
      "StatusDescriptionClient": "Info & intresseanm",
      "UseFilter": 0,
      "SyndicateHouseFormDescriptionGrouped": null,
      "SyndicatePropertyDescriptionGrouped": " Hiss , Inglasad balkong",
      "MapUrl": "https://www.google.com/maps/search/?api=1&query=Kärrhöksgatan+4+55612+Jönköping",
      "QueueCutShow": 1,
      "Street": "Kärrhöksgatan 4",
      "InterestOpens": null,
      "InterestOpensDateString": "",
      "SyndicateMarketPlaceImageAlt": "",
      "RankUpInSearchResult": false,
      "SellerNote": "",
      "Properties": "1,4",
      "HouseForms": "0",
      "ObjectTags": [
        {
          "TagNo": 24,
          "CompanyNo": 1,
          "ObjectNo": "11-069-01-0048",
          "TagText": "Lägenheten visas ej.",
          "TagTextEng": "",
          "TagBackgroundColor": "#1fa12f",
          "TagTextColor": "#ffffff"
        }
      ],
      "GroundRent": ""
    },
    {
      "ObjectMainGroupDescription": null,
      "ObjectSubGroupDescription": null,
      "RowId": "fcb1b903-383f-429b-85b0-1fb77cd5ceb0",
      "SyndicateNo": 1,
      "CompanyNo": 1,
      "AreaNo": "11",
      "HouseNo": "11-087",
      "EntranceNo": "11-087-05",
      "ObjectNo": "11-087-05-0123",
      "ObjectMainGroupNo": 1,
      "ObjectSubGroupNo": 2,
      "ObjectTypeDescription": "2 rum och kök",
      "ObjectAreaSort": 63,
      "ObjectSubDescription": "2 Rum",
      "ObjectArea": "63",
      "ObjectFloor": "7  ",
      "SeekAreaNo": 12,
      "MarketPlaceNo": 107,
      "HouseFormNo": null,
      "PropertyNo": 9,
      "RentPerMonthSort": 5071,
      "RentPerMonth": "5 071",
      "FirstEstateImageUrl": "/vatterhem/files/jpg/thumbs/thumbM6776.jpg",
      "BoardNo": "",
      "Description": "",
      "PlaceName": "Jönköping",
      "SeekAreaDescription": "Råslätt",
      "StreetName": "Havsörnsgatan",
      "StreetNo": 35,
      "StreetChar": "",
      "MarketPlaceDescription": "Torget",
      "CountInterest": 72,
      "FirstInfoTextShort": "<p class=\"MsoNormal\" style=\"margin: 5pt 0cm;\"><span style=\"font-weight: bold;\">Välkommen till Råslätt<br></span>Väl inbäddad mellan Lockebos ängar och Lillåns dalgång hittar du Råslätt, Här trivs mångfalden, här bor Råslättsandan; välkomnande och äkta. Här finns variationer i lägenheter för både den lilla och stora familjen. Hit söker sig såväl studenter som vill bo på Jönköpings störst samlade...",
      "FirstInfoText": "<p class=\"MsoNormal\" style=\"margin: 5pt 0cm;\"><span style=\"font-weight: bold;\">Välkommen till Råslätt<br></span>Väl inbäddad mellan Lockebos ängar och Lillåns dalgång hittar du Råslätt, Här trivs mångfalden, här bor Råslättsandan; välkomnande och äkta. Här finns variationer i lägenheter för både den lilla och stora familjen. Hit söker sig såväl studenter som vill bo på Jönköpings störst samlade studentområde som pensionärer som söker tryggheten och det sociala livet runt boulbanan. Råslätt har något för alla. Alltid med en tilltalande närhet till modern service och ett levande centrum. </p><p class=\"MsoNormal\" style=\"margin: 5pt 0cm;\"><br></p>",
      "EndPeriodMP": "2021-01-31T23:59:59",
      "EndPeriodMPDateString": "2021-01-31",
      "QueueDate": "2017-08-08T00:00:00",
      "QueueDateString": "2017-08-08",
      "QueuePoints": 2534,
      "QueuePositionCut": 5,
      "FreeFrom": "2021-04-01",
      "DesiredFreeFrom": "2021-04-01T00:00:00",
      "DesiredFreeFromString": "2021-04-01",
      "SeekAreaUrl": "https://vatterhem.se/jag-soker-ledigt/vara-omraden/jonkoping/raslatt/",
      "Latitude": "57,7415032",
      "Longitude": "14,1540717",
      "ArriveMarketPlace": "2021-01-25T17:13:01.113",
      "ArriveMarketPlaceDateString": "2021-01-25",
      "PublishingDate": "2021-01-25T17:11:01.003",
      "PublishingDateString": "2021-01-25",
      "IsTradingAdvertisement": false,
      "StatusDescriptionClient": "Info & intresseanm",
      "UseFilter": 0,
      "SyndicateHouseFormDescriptionGrouped": null,
      "SyndicatePropertyDescriptionGrouped": " Balkong , Hiss",
      "MapUrl": "https://www.google.com/maps/search/?api=1&query=Havsörnsgatan+35+55610+Jönköping",
      "QueueCutShow": 1,
      "Street": "Havsörnsgatan 35",
      "InterestOpens": null,
      "InterestOpensDateString": "",
      "SyndicateMarketPlaceImageAlt": "",
      "RankUpInSearchResult": false,
      "SellerNote": "",
      "Properties": "1,9",
      "HouseForms": "0",
      "ObjectTags": [
        {
          "TagNo": 24,
          "CompanyNo": 1,
          "ObjectNo": "11-087-05-0123",
          "TagText": "Lägenheten visas ej.",
          "TagTextEng": "",
          "TagBackgroundColor": "#1fa12f",
          "TagTextColor": "#ffffff"
        }
      ],
      "GroundRent": ""
    },
    {
      "ObjectMainGroupDescription": null,
      "ObjectSubGroupDescription": null,
      "RowId": "f6e6631a-7b4e-4e00-9e20-24ba84db3d38",
      "SyndicateNo": 1,
      "CompanyNo": 1,
      "AreaNo": "12",
      "HouseNo": "12-049",
      "EntranceNo": "12-049-02",
      "ObjectNo": "12-049-02-0032",
      "ObjectMainGroupNo": 1,
      "ObjectSubGroupNo": 1,
      "ObjectTypeDescription": "1 rum och kök",
      "ObjectAreaSort": 41,
      "ObjectSubDescription": "1 Rum",
      "ObjectArea": "41",
      "ObjectFloor": "4  ",
      "SeekAreaNo": 14,
      "MarketPlaceNo": 107,
      "HouseFormNo": null,
      "PropertyNo": 9,
      "RentPerMonthSort": 3944,
      "RentPerMonth": "3 944",
      "FirstEstateImageUrl": "/vatterhem/files/jpg/thumbs/thumbM6149.jpg",
      "BoardNo": "",
      "Description": "",
      "PlaceName": "Jönköping",
      "SeekAreaDescription": "Österängen",
      "StreetName": "Birkagatan",
      "StreetNo": 24,
      "StreetChar": "A",
      "MarketPlaceDescription": "Torget",
      "CountInterest": 134,
      "FirstInfoTextShort": "<p class=\"MsoNormal\" style=\"margin-top:5.0pt;margin-right:0cm;margin-bottom:5.0pt;\nmargin-left:0cm\"><b>Välkommen till Österängen<br></b>Nära till naturen. Nära till staden. Eller rättare sagt städerna, för från Österängen är det lika nära till Jönköping som till Huskvarna. En kombination av det bästa. I både stora och små hus, gamla och nya fastigheter, hittar du här lägenheter i alla storlekar....",
      "FirstInfoText": "<p class=\"MsoNormal\" style=\"margin-top:5.0pt;margin-right:0cm;margin-bottom:5.0pt;\nmargin-left:0cm\"><b>Välkommen till Österängen<br></b>Nära till naturen. Nära till staden. Eller rättare sagt städerna, för från Österängen är det lika nära till Jönköping som till Huskvarna. En kombination av det bästa. I både stora och små hus, gamla och nya fastigheter, hittar du här lägenheter i alla storlekar. Alltid med direkt närhet till gröna miljöer kring husen. Ofta med fin utsikt som standard. Oavsett var i livet du befinner dig är det enkelt att hitta hem här. Goda kommunikationer och ett lokalt centrum med modern service, affärer och butiker gör boendet på Österängen komplett.</p><p class=\"MsoNormal\" style=\"margin-top:5.0pt;margin-right:0cm;margin-bottom:5.0pt;\nmargin-left:0cm\"><o:p></o:p></p>",
      "EndPeriodMP": "2021-01-28T23:59:59",
      "EndPeriodMPDateString": "2021-01-28",
      "QueueDate": "2017-03-23T12:03:00.14",
      "QueueDateString": "2017-03-23",
      "QueuePoints": 2810,
      "QueuePositionCut": 5,
      "FreeFrom": "2021-04-01",
      "DesiredFreeFrom": "2021-02-28T00:00:00",
      "DesiredFreeFromString": "2021-02-28",
      "SeekAreaUrl": "https://vatterhem.se/jag-soker-ledigt/vara-omraden/jonkoping/osterangen/",
      "Latitude": "57,7871624",
      "Longitude": "14,2495887",
      "ArriveMarketPlace": "2021-01-22T10:43:00.843",
      "ArriveMarketPlaceDateString": "2021-01-22",
      "PublishingDate": "2021-01-22T10:41:03.203",
      "PublishingDateString": "2021-01-22",
      "IsTradingAdvertisement": false,
      "StatusDescriptionClient": "Info & intresseanm",
      "UseFilter": 0,
      "SyndicateHouseFormDescriptionGrouped": null,
      "SyndicatePropertyDescriptionGrouped": " Balkong",
      "MapUrl": "https://www.google.com/maps/search/?api=1&query=Birkagatan+24+55465+Jönköping",
      "QueueCutShow": 1,
      "Street": "Birkagatan 24 A",
      "InterestOpens": null,
      "InterestOpensDateString": "",
      "SyndicateMarketPlaceImageAlt": "",
      "RankUpInSearchResult": false,
      "SellerNote": "",
      "Properties": "9",
      "HouseForms": "0",
      "ObjectTags": [
        {
          "TagNo": 24,
          "CompanyNo": 1,
          "ObjectNo": "12-049-02-0032",
          "TagText": "Lägenheten visas ej.",
          "TagTextEng": "",
          "TagBackgroundColor": "#1fa12f",
          "TagTextColor": "#ffffff"
        }
      ],
      "GroundRent": ""
    },
    {
      "ObjectMainGroupDescription": null,
      "ObjectSubGroupDescription": null,
      "RowId": "d2d28f93-c05c-4577-8d6c-8757e1e2cb5d",
      "SyndicateNo": 1,
      "CompanyNo": 1,
      "AreaNo": "12",
      "HouseNo": "12-051",
      "EntranceNo": "12-051-02",
      "ObjectNo": "12-051-02-0009",
      "ObjectMainGroupNo": 1,
      "ObjectSubGroupNo": 1,
      "ObjectTypeDescription": "1 rum och kök",
      "ObjectAreaSort": 41,
      "ObjectSubDescription": "1 Rum",
      "ObjectArea": "41",
      "ObjectFloor": "2  ",
      "SeekAreaNo": 14,
      "MarketPlaceNo": 107,
      "HouseFormNo": null,
      "PropertyNo": null,
      "RentPerMonthSort": 3934,
      "RentPerMonth": "3 934",
      "FirstEstateImageUrl": "/vatterhem/files/jpg/thumbs/thumbM6151.jpg",
      "BoardNo": "",
      "Description": "",
      "PlaceName": "Jönköping",
      "SeekAreaDescription": "Österängen",
      "StreetName": "Birkagatan",
      "StreetNo": 20,
      "StreetChar": "A",
      "MarketPlaceDescription": "Torget",
      "CountInterest": 59,
      "FirstInfoTextShort": "Lägenheten är uppdaterad med individuell ventilation under 2016.Detta \nsäkerställer rätt luftmängd och ett bättre inomhusklimat. Aggregatet är \nplacerat över spis i kök.",
      "FirstInfoText": "Lägenheten är uppdaterad med individuell ventilation under 2016.Detta \nsäkerställer rätt luftmängd och ett bättre inomhusklimat. Aggregatet är \nplacerat över spis i kök.",
      "EndPeriodMP": "2021-01-31T23:59:59",
      "EndPeriodMPDateString": "2021-01-31",
      "QueueDate": "2017-08-27T00:00:00",
      "QueueDateString": "2017-08-27",
      "QueuePoints": 2496,
      "QueuePositionCut": 5,
      "FreeFrom": "2021-05-01",
      "DesiredFreeFrom": null,
      "DesiredFreeFromString": "",
      "SeekAreaUrl": "https://vatterhem.se/jag-soker-ledigt/vara-omraden/jonkoping/osterangen/",
      "Latitude": "57,7872683",
      "Longitude": "14,2480886",
      "ArriveMarketPlace": "2021-01-25T00:01:00.967",
      "ArriveMarketPlaceDateString": "2021-01-25",
      "PublishingDate": "2021-01-25T00:00:00",
      "PublishingDateString": "2021-01-25",
      "IsTradingAdvertisement": false,
      "StatusDescriptionClient": "Info & intresseanm",
      "UseFilter": 0,
      "SyndicateHouseFormDescriptionGrouped": null,
      "SyndicatePropertyDescriptionGrouped": null,
      "MapUrl": "https://www.google.com/maps/search/?api=1&query=Birkagatan+20+55465+Jönköping",
      "QueueCutShow": 1,
      "Street": "Birkagatan 20 A",
      "InterestOpens": null,
      "InterestOpensDateString": "",
      "SyndicateMarketPlaceImageAlt": "",
      "RankUpInSearchResult": false,
      "SellerNote": "",
      "Properties": "0",
      "HouseForms": "0",
      "ObjectTags": [
        {
          "TagNo": 24,
          "CompanyNo": 1,
          "ObjectNo": "12-051-02-0009",
          "TagText": "Lägenheten visas ej.",
          "TagTextEng": "",
          "TagBackgroundColor": "#1fa12f",
          "TagTextColor": "#ffffff"
        }
      ],
      "GroundRent": ""
    },
    {
      "ObjectMainGroupDescription": null,
      "ObjectSubGroupDescription": null,
      "RowId": "1211853c-96a0-4979-a180-63c189868981",
      "SyndicateNo": 1,
      "CompanyNo": 1,
      "AreaNo": "14",
      "HouseNo": "14-021",
      "EntranceNo": "14-021-02",
      "ObjectNo": "14-021-02-0015",
      "ObjectMainGroupNo": 1,
      "ObjectSubGroupNo": 2,
      "ObjectTypeDescription": "2 rum med kokvrå",
      "ObjectAreaSort": 42,
      "ObjectSubDescription": "2 Rum",
      "ObjectArea": "42",
      "ObjectFloor": "3  ",
      "SeekAreaNo": 112,
      "MarketPlaceNo": 107,
      "HouseFormNo": null,
      "PropertyNo": 9,
      "RentPerMonthSort": 4074,
      "RentPerMonth": "4 074",
      "FirstEstateImageUrl": "/vatterhem/files/jpg/thumbs/thumbM1690.jpg",
      "BoardNo": "",
      "Description": "",
      "PlaceName": "Jönköping",
      "SeekAreaDescription": "Gräshagen",
      "StreetName": "Fornkullegatan",
      "StreetNo": 1,
      "StreetChar": "A",
      "MarketPlaceDescription": "Torget",
      "CountInterest": 392,
      "FirstInfoTextShort": "<div><span style=\"font-weight: bold;\">Välkommen till Gräshagen</span></div><div>Njut av Vattenledningsparkens mångfald under årets alla månader. Se hur jordbruket på Tokarps vida ängar tar fart på våren. Gräshagen har naturen som närmsta granne. Samtidigt som du via effektiva kommunikationer tar dig snabbt in till stan. Ett lokalt centrum med livsmedelsaffär och restauranger finns också för att...",
      "FirstInfoText": "<div><span style=\"font-weight: bold;\">Välkommen till Gräshagen</span></div><div>Njut av Vattenledningsparkens mångfald under årets alla månader. Se hur jordbruket på Tokarps vida ängar tar fart på våren. Gräshagen har naturen som närmsta granne. Samtidigt som du via effektiva kommunikationer tar dig snabbt in till stan. Ett lokalt centrum med livsmedelsaffär och restauranger finns också för att underlätta vardagen. Liksom närheten till andra viktiga servicefunktioner. </div><div><br></div><div><br></div>",
      "EndPeriodMP": "2021-01-27T23:59:59",
      "EndPeriodMPDateString": "2021-01-27",
      "QueueDate": "2016-09-23T00:00:00",
      "QueueDateString": "2016-09-23",
      "QueuePoints": 3172,
      "QueuePositionCut": 5,
      "FreeFrom": "2021-05-01",
      "DesiredFreeFrom": "2021-05-01T00:00:00",
      "DesiredFreeFromString": "2021-05-01",
      "SeekAreaUrl": "https://vatterhem.se/jag-soker-ledigt/vara-omraden/jonkoping/grashagen/",
      "Latitude": "57,7638658",
      "Longitude": "14,1351989",
      "ArriveMarketPlace": "2021-01-21T00:01:00.27",
      "ArriveMarketPlaceDateString": "2021-01-21",
      "PublishingDate": "2021-01-21T00:00:00",
      "PublishingDateString": "2021-01-21",
      "IsTradingAdvertisement": false,
      "StatusDescriptionClient": "Info & intresseanm",
      "UseFilter": 0,
      "SyndicateHouseFormDescriptionGrouped": null,
      "SyndicatePropertyDescriptionGrouped": " Balkong",
      "MapUrl": "https://www.google.com/maps/search/?api=1&query=Fornkullegatan+1+55473+Jönköping",
      "QueueCutShow": 1,
      "Street": "Fornkullegatan 1 A",
      "InterestOpens": null,
      "InterestOpensDateString": "",
      "SyndicateMarketPlaceImageAlt": "",
      "RankUpInSearchResult": false,
      "SellerNote": "",
      "Properties": "9",
      "HouseForms": "0",
      "ObjectTags": [
        {
          "TagNo": 24,
          "CompanyNo": 1,
          "ObjectNo": "14-021-02-0015",
          "TagText": "Lägenheten visas ej.",
          "TagTextEng": "",
          "TagBackgroundColor": "#1fa12f",
          "TagTextColor": "#ffffff"
        }
      ],
      "GroundRent": ""
    },
    {
      "ObjectMainGroupDescription": null,
      "ObjectSubGroupDescription": null,
      "RowId": "61eb4716-44de-4949-9e0b-4d44460b85c6",
      "SyndicateNo": 1,
      "CompanyNo": 1,
      "AreaNo": "14",
      "HouseNo": "14-036",
      "EntranceNo": "14-036-01",
      "ObjectNo": "14-036-01-0027",
      "ObjectMainGroupNo": 1,
      "ObjectSubGroupNo": 1,
      "ObjectTypeDescription": "1 rum och kök",
      "ObjectAreaSort": 40,
      "ObjectSubDescription": "1 Rum",
      "ObjectArea": "40",
      "ObjectFloor": "5  ",
      "SeekAreaNo": 113,
      "MarketPlaceNo": 107,
      "HouseFormNo": null,
      "PropertyNo": 9,
      "RentPerMonthSort": 4158,
      "RentPerMonth": "4 158",
      "FirstEstateImageUrl": "/vatterhem/files/jpg/thumbs/thumbM1630.jpg",
      "BoardNo": "",
      "Description": "",
      "PlaceName": "Jönköping",
      "SeekAreaDescription": "Kristinedal",
      "StreetName": "Solstickegatan",
      "StreetNo": 14,
      "StreetChar": "",
      "MarketPlaceDescription": "Torget",
      "CountInterest": 164,
      "FirstInfoTextShort": "<p class=\"MsoNormal\" style=\"margin-top:5.0pt;margin-right:0cm;margin-bottom:5.0pt;\nmargin-left:0cm\"><span style=\"font-weight: bold;\">Välkommen till Kristinedal<br></span>I vackra Friaredalens förlängning med Vattenledningsparken och stadsparken som grannar hittar du Kristinedal. Sådär lite lagom nära citykärnan för att ha gångavstånd, men ändå undvika den där allra mest intensiva stadspulsen....",
      "FirstInfoText": "<p class=\"MsoNormal\" style=\"margin-top:5.0pt;margin-right:0cm;margin-bottom:5.0pt;\nmargin-left:0cm\"><span style=\"font-weight: bold;\">Välkommen till Kristinedal<br></span>I vackra Friaredalens förlängning med Vattenledningsparken och stadsparken som grannar hittar du Kristinedal. Sådär lite lagom nära citykärnan för att ha gångavstånd, men ändå undvika den där allra mest intensiva stadspulsen. Fastigheterna på Kristinedalsgatan, Solstickegatan och Ståltorpsgatan är moderna och attraktiva för boende i alla åldrar.</p><p class=\"MsoNormal\" style=\"margin-top:5.0pt;margin-right:0cm;margin-bottom:5.0pt;\nmargin-left:0cm\"><br></p><p class=\"MsoNormal\" style=\"margin-top:5.0pt;margin-right:0cm;margin-bottom:5.0pt;\nmargin-left:0cm\"><br></p><p class=\"MsoNormal\" style=\"margin-top:5.0pt;margin-right:0cm;margin-bottom:5.0pt;\nmargin-left:0cm\"><br></p><p class=\"MsoNormal\" style=\"margin-top:5.0pt;margin-right:0cm;margin-bottom:5.0pt;\nmargin-left:0cm\"><o:p></o:p></p>",
      "EndPeriodMP": "2021-01-31T23:59:59",
      "EndPeriodMPDateString": "2021-01-31",
      "QueueDate": "2016-07-05T13:08:50.807",
      "QueueDateString": "2016-07-05",
      "QueuePoints": 3332,
      "QueuePositionCut": 5,
      "FreeFrom": "2021-05-01",
      "DesiredFreeFrom": null,
      "DesiredFreeFromString": "",
      "SeekAreaUrl": "https://vatterhem.se/jag-soker-ledigt/vara-omraden/jonkoping/kristinedal/",
      "Latitude": "57,7801907",
      "Longitude": "14,1485539",
      "ArriveMarketPlace": "2021-01-25T00:01:00.967",
      "ArriveMarketPlaceDateString": "2021-01-25",
      "PublishingDate": "2021-01-25T00:00:00",
      "PublishingDateString": "2021-01-25",
      "IsTradingAdvertisement": false,
      "StatusDescriptionClient": "Info & intresseanm",
      "UseFilter": 0,
      "SyndicateHouseFormDescriptionGrouped": null,
      "SyndicatePropertyDescriptionGrouped": " Balkong , Hiss",
      "MapUrl": "https://www.google.com/maps/search/?api=1&query=Solstickegatan+14+55314+Jönköping",
      "QueueCutShow": 1,
      "Street": "Solstickegatan 14",
      "InterestOpens": null,
      "InterestOpensDateString": "",
      "SyndicateMarketPlaceImageAlt": "",
      "RankUpInSearchResult": false,
      "SellerNote": "",
      "Properties": "1,9",
      "HouseForms": "0",
      "ObjectTags": [
        {
          "TagNo": 24,
          "CompanyNo": 1,
          "ObjectNo": "14-036-01-0027",
          "TagText": "Lägenheten visas ej.",
          "TagTextEng": "",
          "TagBackgroundColor": "#1fa12f",
          "TagTextColor": "#ffffff"
        }
      ],
      "GroundRent": ""
    },
    {
      "ObjectMainGroupDescription": null,
      "ObjectSubGroupDescription": null,
      "RowId": "243566c9-288e-406e-b3f0-3003fead7fef",
      "SyndicateNo": 1,
      "CompanyNo": 1,
      "AreaNo": "16",
      "HouseNo": "16-040",
      "EntranceNo": "16-040-04",
      "ObjectNo": "16-040-04-0074",
      "ObjectMainGroupNo": 1,
      "ObjectSubGroupNo": 4,
      "ObjectTypeDescription": "4 rum och kök",
      "ObjectAreaSort": 106,
      "ObjectSubDescription": "4 Rum",
      "ObjectArea": "106",
      "ObjectFloor": "5  ",
      "SeekAreaNo": 16,
      "MarketPlaceNo": 107,
      "HouseFormNo": null,
      "PropertyNo": 4,
      "RentPerMonthSort": 14334,
      "RentPerMonth": "14 334",
      "FirstEstateImageUrl": "/vatterhem/files/jpg/thumbs/thumbM6459.jpg",
      "BoardNo": "",
      "Description": "",
      "PlaceName": "Jönköping",
      "SeekAreaDescription": "Strandängen",
      "StreetName": "Ceciliagatan",
      "StreetNo": 6,
      "StreetChar": "",
      "MarketPlaceDescription": "Torget",
      "CountInterest": 25,
      "FirstInfoTextShort": "<p class=\"MsoNormal\" style=\"margin: 5pt 0cm;\"><b>Välkommen till Strandängen</b><o:p></o:p></p><p class=\"MsoNormal\" style=\"margin: 5pt 0cm;\">Jönköpings nyaste stadsdel har Vättern som närmsta granne. Här kan du bo i det arkitekturprisade Ormhuset eller i något av våra nio Kultur- och Gatuhus. Och expansionen på detta intressanta område lär inte ta slut där. Vill du sedan ta dig in till stan är det...",
      "FirstInfoText": "<p class=\"MsoNormal\" style=\"margin: 5pt 0cm;\"><b>Välkommen till Strandängen</b><o:p></o:p></p><p class=\"MsoNormal\" style=\"margin: 5pt 0cm;\">Jönköpings nyaste stadsdel har Vättern som närmsta granne. Här kan du bo i det arkitekturprisade Ormhuset eller i något av våra nio Kultur- och Gatuhus. Och expansionen på detta intressanta område lär inte ta slut där. Vill du sedan ta dig in till stan är det bara 3,5 kilometer till stadskärnan. Säg den som inte vill bo där Vättern ger utsikt och rymd - där fält, skog och ängar ramar in och skyddar?</p><p class=\"MsoNormal\" style=\"margin: 5pt 0cm;\"><br></p>",
      "EndPeriodMP": "2021-01-31T23:59:59",
      "EndPeriodMPDateString": "2021-01-31",
      "QueueDate": "2019-01-11T11:42:22.42",
      "QueueDateString": "2019-01-11",
      "QueuePoints": 1492,
      "QueuePositionCut": 5,
      "FreeFrom": "2021-05-01",
      "DesiredFreeFrom": null,
      "DesiredFreeFromString": "",
      "SeekAreaUrl": "https://www.vatterhem.se/jag-soker-ledigt/vara-omraden/jonkoping/strandangen/",
      "Latitude": "57,810452",
      "Longitude": "14,153223",
      "ArriveMarketPlace": "2021-01-25T00:01:00.967",
      "ArriveMarketPlaceDateString": "2021-01-25",
      "PublishingDate": "2021-01-25T00:00:00",
      "PublishingDateString": "2021-01-25",
      "IsTradingAdvertisement": false,
      "StatusDescriptionClient": "Info & intresseanm",
      "UseFilter": 0,
      "SyndicateHouseFormDescriptionGrouped": null,
      "SyndicatePropertyDescriptionGrouped": " Balkong , Hiss , Inglasad balkong",
      "MapUrl": "https://www.google.com/maps/search/?api=1&query=Ceciliagatan+6+55310+Jönköping",
      "QueueCutShow": 1,
      "Street": "Ceciliagatan 6",
      "InterestOpens": null,
      "InterestOpensDateString": "",
      "SyndicateMarketPlaceImageAlt": "",
      "RankUpInSearchResult": false,
      "SellerNote": "",
      "Properties": "1,4,9",
      "HouseForms": "0",
      "ObjectTags": [
        {
          "TagNo": 24,
          "CompanyNo": 1,
          "ObjectNo": "16-040-04-0074",
          "TagText": "Lägenheten visas ej.",
          "TagTextEng": "",
          "TagBackgroundColor": "#1fa12f",
          "TagTextColor": "#ffffff"
        }
      ],
      "GroundRent": ""
    },
    {
      "ObjectMainGroupDescription": null,
      "ObjectSubGroupDescription": null,
      "RowId": "a938e685-d2ed-4462-8d6a-523e1a155deb",
      "SyndicateNo": 1,
      "CompanyNo": 1,
      "AreaNo": "16",
      "HouseNo": "16-047",
      "EntranceNo": "16-047-01",
      "ObjectNo": "16-047-01-0001",
      "ObjectMainGroupNo": 1,
      "ObjectSubGroupNo": 3,
      "ObjectTypeDescription": "3 rum och kök",
      "ObjectAreaSort": 83,
      "ObjectSubDescription": "3 Rum",
      "ObjectArea": "83",
      "ObjectFloor": "0  ",
      "SeekAreaNo": 16,
      "MarketPlaceNo": 107,
      "HouseFormNo": null,
      "PropertyNo": 5,
      "RentPerMonthSort": 10391,
      "RentPerMonth": "10 391",
      "FirstEstateImageUrl": "/vatterhem/files/jpg/thumbs/thumbM6974.jpg",
      "BoardNo": "",
      "Description": "",
      "PlaceName": "Jönköping",
      "SeekAreaDescription": "Strandängen",
      "StreetName": "Ceciliagatan",
      "StreetNo": 46,
      "StreetChar": "",
      "MarketPlaceDescription": "Torget",
      "CountInterest": 19,
      "FirstInfoTextShort": "<p class=\"MsoNormal\" style=\"margin: 5pt 0cm;\"><b>Välkommen till Strandängen</b><o:p></o:p></p><p class=\"MsoNormal\" style=\"margin: 5pt 0cm;\">Jönköpings nyaste stadsdel har Vättern som närmsta granne. Här kan du bo i det arkitekturprisade Ormhuset eller i något av våra nio Kultur- och Gatuhus. Och expansionen på detta intressanta område lär inte ta slut där. Vill du sedan ta dig in till stan är det...",
      "FirstInfoText": "<p class=\"MsoNormal\" style=\"margin: 5pt 0cm;\"><b>Välkommen till Strandängen</b><o:p></o:p></p><p class=\"MsoNormal\" style=\"margin: 5pt 0cm;\">Jönköpings nyaste stadsdel har Vättern som närmsta granne. Här kan du bo i det arkitekturprisade Ormhuset eller i något av våra nio Kultur- och Gatuhus. Och expansionen på detta intressanta område lär inte ta slut där. Vill du sedan ta dig in till stan är det bara 3,5 kilometer till stadskärnan. Säg den som inte vill bo där Vättern ger utsikt och rymd - där fält, skog och ängar ramar in och skyddar?</p><p class=\"MsoNormal\" style=\"margin: 5pt 0cm;\"><br></p>",
      "EndPeriodMP": "2021-01-31T23:59:59",
      "EndPeriodMPDateString": "2021-01-31",
      "QueueDate": "2017-05-22T00:00:00",
      "QueueDateString": "2017-05-22",
      "QueuePoints": 2326,
      "QueuePositionCut": 5,
      "FreeFrom": "2021-05-01",
      "DesiredFreeFrom": "2021-02-09T00:00:00",
      "DesiredFreeFromString": "2021-02-09",
      "SeekAreaUrl": "https://www.vatterhem.se/jag-soker-ledigt/vara-omraden/jonkoping/strandangen/",
      "Latitude": "57,811283",
      "Longitude": "14,156688",
      "ArriveMarketPlace": "2021-01-25T17:23:01.02",
      "ArriveMarketPlaceDateString": "2021-01-25",
      "PublishingDate": "2021-01-25T17:21:02.96",
      "PublishingDateString": "2021-01-25",
      "IsTradingAdvertisement": false,
      "StatusDescriptionClient": "Info & intresseanm",
      "UseFilter": 0,
      "SyndicateHouseFormDescriptionGrouped": null,
      "SyndicatePropertyDescriptionGrouped": " Hiss , Uteplats",
      "MapUrl": "https://www.google.com/maps/search/?api=1&query=Ceciliagatan+46+55310+Jönköping",
      "QueueCutShow": 1,
      "Street": "Ceciliagatan 46",
      "InterestOpens": null,
      "InterestOpensDateString": "",
      "SyndicateMarketPlaceImageAlt": "",
      "RankUpInSearchResult": false,
      "SellerNote": "",
      "Properties": "1,5",
      "HouseForms": "0",
      "ObjectTags": [
        {
          "TagNo": 29,
          "CompanyNo": 1,
          "ObjectNo": "16-047-01-0001",
          "TagText": "Rökfritt boende-Lägenheten visas ej.",
          "TagTextEng": "",
          "TagBackgroundColor": "#a1411f",
          "TagTextColor": "#ffffff"
        }
      ],
      "GroundRent": ""
    },
    {
      "ObjectMainGroupDescription": null,
      "ObjectSubGroupDescription": null,
      "RowId": "1990305f-b1f8-49f4-984f-258fb47ff0fd",
      "SyndicateNo": 1,
      "CompanyNo": 1,
      "AreaNo": "17",
      "HouseNo": "17-035",
      "EntranceNo": "17-035-03",
      "ObjectNo": "17-035-03-0312",
      "ObjectMainGroupNo": 1,
      "ObjectSubGroupNo": 3,
      "ObjectTypeDescription": "3 rum och kök",
      "ObjectAreaSort": 77,
      "ObjectSubDescription": "3 Rum",
      "ObjectArea": "77",
      "ObjectFloor": "3 v",
      "SeekAreaNo": 201,
      "MarketPlaceNo": 107,
      "HouseFormNo": null,
      "PropertyNo": 1,
      "RentPerMonthSort": 6324,
      "RentPerMonth": "6 324",
      "FirstEstateImageUrl": "/vatterhem/files/jpg/thumbs/thumbM6077.jpg",
      "BoardNo": "",
      "Description": "",
      "PlaceName": "Huskvarna",
      "SeekAreaDescription": "Öxnehaga",
      "StreetName": "Lahagsgatan",
      "StreetNo": 15,
      "StreetChar": "",
      "MarketPlaceDescription": "Torget",
      "CountInterest": 129,
      "FirstInfoTextShort": "<p class=\"MsoNormal\" style=\"margin: 5pt 0cm;\"><b>Välkommen till Öxnehaga</b><o:p></o:p></p><p class=\"MsoNormal\" style=\"margin: 5pt 0cm;\">Vätterns vackra vyer för ögonen, Bondberget och Öxnegårdens rekreationskraft i ryggen. Öxnehaga är både stad och natur. Här finns boende för alla, lägenheter i stort och smått, oavsett var du befinner dig i livet. Från barnens generösa lekytor till...",
      "FirstInfoText": "<p class=\"MsoNormal\" style=\"margin: 5pt 0cm;\"><b>Välkommen till Öxnehaga</b><o:p></o:p></p><p class=\"MsoNormal\" style=\"margin: 5pt 0cm;\">Vätterns vackra vyer för ögonen, Bondberget och Öxnegårdens rekreationskraft i ryggen. Öxnehaga är både stad och natur. Här finns boende för alla, lägenheter i stort och smått, oavsett var du befinner dig i livet. Från barnens generösa lekytor till trygghetsboendets lugn och ro. Goda kommunikationer, god samhällelig service och affärsutbud gör Öxnehaga till ett område där du och familjen får utrymme att växa. </p>",
      "EndPeriodMP": "2021-01-31T23:59:59",
      "EndPeriodMPDateString": "2021-01-31",
      "QueueDate": "2016-10-04T00:00:00",
      "QueueDateString": "2016-10-04",
      "QueuePoints": 3150,
      "QueuePositionCut": 5,
      "FreeFrom": "2021-05-01",
      "DesiredFreeFrom": "2021-04-01T00:00:00",
      "DesiredFreeFromString": "2021-04-01",
      "SeekAreaUrl": "https://vatterhem.se/jag-soker-ledigt/vara-omraden/huskvarna/oxnehaga/",
      "Latitude": "57,7766563",
      "Longitude": "14,2669474",
      "ArriveMarketPlace": "2021-01-25T00:01:00.967",
      "ArriveMarketPlaceDateString": "2021-01-25",
      "PublishingDate": "2021-01-25T00:00:00",
      "PublishingDateString": "2021-01-25",
      "IsTradingAdvertisement": false,
      "StatusDescriptionClient": "Info & intresseanm",
      "UseFilter": 0,
      "SyndicateHouseFormDescriptionGrouped": null,
      "SyndicatePropertyDescriptionGrouped": " Hiss , Inglasad balkong",
      "MapUrl": "https://www.google.com/maps/search/?api=1&query=Lahagsgatan+15+56151+Huskvarna",
      "QueueCutShow": 1,
      "Street": "Lahagsgatan 15",
      "InterestOpens": null,
      "InterestOpensDateString": "",
      "SyndicateMarketPlaceImageAlt": "",
      "RankUpInSearchResult": false,
      "SellerNote": "",
      "Properties": "1,4",
      "HouseForms": "0",
      "ObjectTags": [
        {
          "TagNo": 24,
          "CompanyNo": 1,
          "ObjectNo": "17-035-03-0312",
          "TagText": "Lägenheten visas ej.",
          "TagTextEng": "",
          "TagBackgroundColor": "#1fa12f",
          "TagTextColor": "#ffffff"
        }
      ],
      "GroundRent": ""
    },
    {
      "ObjectMainGroupDescription": null,
      "ObjectSubGroupDescription": null,
      "RowId": "30d3d63a-d16c-4aaa-a319-a7cd1ef46923",
      "SyndicateNo": 1,
      "CompanyNo": 1,
      "AreaNo": "17",
      "HouseNo": "17-097",
      "EntranceNo": "17-097-01",
      "ObjectNo": "17-097-01-0985",
      "ObjectMainGroupNo": 1,
      "ObjectSubGroupNo": 2,
      "ObjectTypeDescription": "2 rum och kök",
      "ObjectAreaSort": 72,
      "ObjectSubDescription": "2 Rum",
      "ObjectArea": "72",
      "ObjectFloor": "2 h",
      "SeekAreaNo": 201,
      "MarketPlaceNo": 107,
      "HouseFormNo": 51,
      "PropertyNo": 9,
      "RentPerMonthSort": 6125,
      "RentPerMonth": "6 125",
      "FirstEstateImageUrl": "/vatterhem/files/jpg/thumbs/thumbM6809.jpg",
      "BoardNo": "",
      "Description": "",
      "PlaceName": "Huskvarna",
      "SeekAreaDescription": "Öxnehaga",
      "StreetName": "Oxhagsgatan",
      "StreetNo": 11,
      "StreetChar": "",
      "MarketPlaceDescription": "Torget",
      "CountInterest": 1,
      "FirstInfoTextShort": "<p class=\"MsoNormal\" style=\"margin: 5pt 0cm;\"><b>Välkommen till Öxnehaga</b><o:p></o:p></p><p class=\"MsoNormal\" style=\"margin: 5pt 0cm;\">Vätterns vackra vyer för ögonen, Bondberget och Öxnegårdens rekreationskraft i ryggen. Öxnehaga är både stad och natur. Här finns boende för alla, lägenheter i stort och smått, oavsett var du befinner dig i livet. Från barnens generösa lekytor till...",
      "FirstInfoText": "<p class=\"MsoNormal\" style=\"margin: 5pt 0cm;\"><b>Välkommen till Öxnehaga</b><o:p></o:p></p><p class=\"MsoNormal\" style=\"margin: 5pt 0cm;\">Vätterns vackra vyer för ögonen, Bondberget och Öxnegårdens rekreationskraft i ryggen. Öxnehaga är både stad och natur. Här finns boende för alla, lägenheter i stort och smått, oavsett var du befinner dig i livet. Från barnens generösa lekytor till trygghetsboendets lugn och ro. Goda kommunikationer, god samhällelig service och affärsutbud gör Öxnehaga till ett område där du och familjen får utrymme att växa. </p>",
      "EndPeriodMP": "2021-01-27T23:59:59",
      "EndPeriodMPDateString": "2021-01-27",
      "QueueDate": null,
      "QueueDateString": "",
      "QueuePoints": 0,
      "QueuePositionCut": 5,
      "FreeFrom": "2021-05-01",
      "DesiredFreeFrom": "2021-01-26T07:15:03.423",
      "DesiredFreeFromString": "2021-01-26",
      "SeekAreaUrl": "https://vatterhem.se/jag-soker-ledigt/vara-omraden/huskvarna/oxnehaga/",
      "Latitude": "57,7738918",
      "Longitude": "14,2702296",
      "ArriveMarketPlace": "2021-01-21T12:41:00.81",
      "ArriveMarketPlaceDateString": "2021-01-21",
      "PublishingDate": "2021-01-21T12:39:31.093",
      "PublishingDateString": "2021-01-21",
      "IsTradingAdvertisement": false,
      "StatusDescriptionClient": "Info & intresseanm",
      "UseFilter": 0,
      "SyndicateHouseFormDescriptionGrouped": " Trygghetsboende",
      "SyndicatePropertyDescriptionGrouped": " Balkong , Hiss",
      "MapUrl": "https://www.google.com/maps/search/?api=1&query=Oxhagsgatan+11+56150+Huskvarna",
      "QueueCutShow": 1,
      "Street": "Oxhagsgatan 11",
      "InterestOpens": null,
      "InterestOpensDateString": "",
      "SyndicateMarketPlaceImageAlt": "",
      "RankUpInSearchResult": false,
      "SellerNote": "",
      "Properties": "1,9",
      "HouseForms": "51",
      "ObjectTags": [
        {
          "TagNo": 17,
          "CompanyNo": 1,
          "ObjectNo": "17-097-01-0985",
          "TagText": "Trygghetsboende  Ingen visning",
          "TagTextEng": "",
          "TagBackgroundColor": "#9126a8",
          "TagTextColor": "#ffffff"
        }
      ],
      "GroundRent": ""
    },
    {
      "ObjectMainGroupDescription": null,
      "ObjectSubGroupDescription": null,
      "RowId": "7f3e22d5-9fd5-409b-a39a-0175bb84609d",
      "SyndicateNo": 1,
      "CompanyNo": 1,
      "AreaNo": "17",
      "HouseNo": "17-103",
      "EntranceNo": "17-103-02",
      "ObjectNo": "17-103-02-1067",
      "ObjectMainGroupNo": 1,
      "ObjectSubGroupNo": 2,
      "ObjectTypeDescription": "2 rum och kök",
      "ObjectAreaSort": 63,
      "ObjectSubDescription": "2 Rum",
      "ObjectArea": "63",
      "ObjectFloor": "2 h",
      "SeekAreaNo": 201,
      "MarketPlaceNo": 120,
      "HouseFormNo": null,
      "PropertyNo": 4,
      "RentPerMonthSort": 5401,
      "RentPerMonth": "5 401",
      "FirstEstateImageUrl": "/vatterhem/files/jpg/thumbs/thumbM6022.jpg",
      "BoardNo": "",
      "Description": "",
      "PlaceName": "Huskvarna",
      "SeekAreaDescription": "Öxnehaga",
      "StreetName": "Kohagsgatan",
      "StreetNo": 101,
      "StreetChar": "",
      "MarketPlaceDescription": "Lottning",
      "CountInterest": 115,
      "FirstInfoTextShort": "<p class=\"MsoNormal\" style=\"margin: 5pt 0cm;\"><b>Välkommen till Öxnehaga</b><o:p></o:p></p><p class=\"MsoNormal\" style=\"margin: 5pt 0cm;\">Vätterns vackra vyer för ögonen, Bondberget och Öxnegårdens rekreationskraft i ryggen. Öxnehaga är både stad och natur. Här finns boende för alla, lägenheter i stort och smått, oavsett var du befinner dig i livet. Från barnens generösa lekytor till...",
      "FirstInfoText": "<p class=\"MsoNormal\" style=\"margin: 5pt 0cm;\"><b>Välkommen till Öxnehaga</b><o:p></o:p></p><p class=\"MsoNormal\" style=\"margin: 5pt 0cm;\">Vätterns vackra vyer för ögonen, Bondberget och Öxnegårdens rekreationskraft i ryggen. Öxnehaga är både stad och natur. Här finns boende för alla, lägenheter i stort och smått, oavsett var du befinner dig i livet. Från barnens generösa lekytor till trygghetsboendets lugn och ro. Goda kommunikationer, god samhällelig service och affärsutbud gör Öxnehaga till ett område där du och familjen får utrymme att växa. </p>",
      "EndPeriodMP": "2021-01-26T19:00:00",
      "EndPeriodMPDateString": "2021-01-26 19:00",
      "QueueDate": null,
      "QueueDateString": "",
      "QueuePoints": 0,
      "QueuePositionCut": 5,
      "FreeFrom": "2021-03-01",
      "DesiredFreeFrom": "2021-03-01T00:00:00",
      "DesiredFreeFromString": "2021-03-01",
      "SeekAreaUrl": "https://vatterhem.se/jag-soker-ledigt/vara-omraden/huskvarna/oxnehaga/",
      "Latitude": "57,7740955",
      "Longitude": "14,2593267",
      "ArriveMarketPlace": "2021-01-25T16:17:00.653",
      "ArriveMarketPlaceDateString": "2021-01-25",
      "PublishingDate": "2021-01-25T16:15:04.857",
      "PublishingDateString": "2021-01-25",
      "IsTradingAdvertisement": false,
      "StatusDescriptionClient": "Info & intresseanm",
      "UseFilter": 0,
      "SyndicateHouseFormDescriptionGrouped": null,
      "SyndicatePropertyDescriptionGrouped": " Hiss , Inglasad balkong",
      "MapUrl": "https://www.google.com/maps/search/?api=1&query=Kohagsgatan+101+56149+Huskvarna",
      "QueueCutShow": 1,
      "Street": "Kohagsgatan 101",
      "InterestOpens": "2021-01-25T19:00:00",
      "InterestOpensDateString": "2021-01-25 19:00:00",
      "SyndicateMarketPlaceImageAlt": "",
      "RankUpInSearchResult": false,
      "SellerNote": "",
      "Properties": "1,4",
      "HouseForms": "0",
      "ObjectTags": [
        {
          "TagNo": 24,
          "CompanyNo": 1,
          "ObjectNo": "17-103-02-1067",
          "TagText": "Lägenheten visas ej.",
          "TagTextEng": "",
          "TagBackgroundColor": "#1fa12f",
          "TagTextColor": "#ffffff"
        }
      ],
      "GroundRent": ""
    }
  ],
  "TotalCount": 11,
  "ObjectMainGroupDescription": "",
  "ObjectMainGroupNo": 0
}
